django_serverless_cron/__init__.py
django_serverless_cron/admin.py
django_serverless_cron/app_settings.py
django_serverless_cron/apps.py
django_serverless_cron/models.py
django_serverless_cron/services.py
django_serverless_cron/urls.py
django_serverless_cron/utils.py
django_serverless_cron/views.py
django_serverless_cron/management/__init__.py
django_serverless_cron/management/commands/__init__.py
django_serverless_cron/management/commands/serverless_cron_run.py
django_serverless_cron/migrations/0001_initial.py
django_serverless_cron/migrations/__init__.py
django_serverless_cron-0.1.3.dist-info/AUTHORS.rst
django_serverless_cron-0.1.3.dist-info/LICENSE
django_serverless_cron-0.1.3.dist-info/METADATA
django_serverless_cron-0.1.3.dist-info/WHEEL
django_serverless_cron-0.1.3.dist-info/top_level.txt
django_serverless_cron-0.1.3.dist-info/RECORD
