Metadata-Version: 2.1
Name: django-serverless-cron
Version: 0.1.3
Summary: Django Serverless Cron 🦡
Home-page: https://github.com/paulonteri/django-serverless-cron
Author: Paul Onteri
Author-email: me@paulonteri.com
License: MIT
Keywords: django-serverless-cron
Platform: UNKNOWN
Classifier: Development Status :: 3 - Alpha
Classifier: Framework :: Django :: 3.1
Classifier: Framework :: Django :: 3.2
Classifier: Intended Audience :: Developers
Classifier: License :: OSI Approved :: BSD License
Classifier: Natural Language :: English
Classifier: Programming Language :: Python :: 3.5
Classifier: Programming Language :: Python :: 3.6
Classifier: Programming Language :: Python :: 3.7
Classifier: Programming Language :: Python :: 3.8
Classifier: Programming Language :: Python :: 3.9
Classifier: Programming Language :: Python :: 3.10
License-File: LICENSE
License-File: AUTHORS.rst
Requires-Dist: coverage (==4.4.1)
